pygenpdf_json-0.1.15.dist-info/METADATA
pygenpdf_json-0.1.15.dist-info/WHEEL
pygenpdf_json-0.1.15.dist-info/licenses/LICENSE
pygenpdf_json.libs/libsqlite3-2e6eef9a.so.0
pygenpdf_json/__init__.py
pygenpdf_json/pygenpdf_json.cpython-311-x86_64-linux-gnu.so
pygenpdf_json-0.1.15.dist-info/RECORD
