Metadata-Version: 2.4
Name: pygenpdf_json
Version: 0.1.15
Classifier: Development Status :: 4 - Beta
Classifier: Programming Language :: Rust
Classifier: License :: OSI Approved :: GNU General Public License v3 (GPLv3)
Classifier: Programming Language :: Python :: Implementation :: CPython
Classifier: Programming Language :: Python :: Implementation :: PyPy
Classifier: Programming Language :: Python
Classifier: Programming Language :: Python :: 3
Classifier: Topic :: Software Development :: Libraries
Classifier: Topic :: Software Development :: Libraries :: Python Modules
License-File: LICENSE
Summary: Python bindings to Rust's genpdf-json library (PDF generator)
Home-Page: https://gitlab.com/numaelis/pygenpdf_json
Maintainer-email: Numael Garay <mantrixsoft@gmail.com>
License-Expression: GPL3
Requires-Python: >=3.8
Project-URL: homepage, https://gitlab.com/numaelis/pygenpdf_json
